serializable_trees/__init__.py
serializable_trees/__main__.py
serializable_trees/basics.py
serializable_trees/py.typed
serializable_trees/trees.py
serializable_trees-0.5.1.dist-info/LICENSE
serializable_trees-0.5.1.dist-info/METADATA
serializable_trees-0.5.1.dist-info/WHEEL
serializable_trees-0.5.1.dist-info/entry_points.txt
serializable_trees-0.5.1.dist-info/top_level.txt
serializable_trees-0.5.1.dist-info/RECORD
