Metadata-Version: 2.1
Name: serializable-trees
Version: 0.5.1
Summary: Serializable tree datatypes for Python
Author-email: Rainer Schwarzbach <undisclosed@example.com>
License: MIT License
Project-URL: Homepage, https://gitlab.com/blackstream-x/serializable-trees
Project-URL: Documentation, https://blackstream-x.gitlab.io/serializable-trees
Project-URL: CI, https://gitlab.com/blackstream-x/serializable-trees/-/pipelines
Project-URL: Bug Tracker, https://gitlab.com/blackstream-x/serializable-trees/-/issues
Project-URL: Source Code, https://gitlab.com/blackstream-x/serializable-trees.git
Keywords: json,yaml,tree,node,datatype
Classifier: Development Status :: 4 - Beta
Classifier: Intended Audience :: Developers
Classifier: License :: OSI Approved :: MIT License
Classifier: Operating System :: OS Independent
Classifier: Programming Language :: Python :: 3
Classifier: Programming Language :: Python :: 3.8
Classifier: Programming Language :: Python :: 3.9
Classifier: Programming Language :: Python :: 3.10
Classifier: Programming Language :: Python :: 3.11
Classifier: Programming Language :: Python :: 3.12
Classifier: Programming Language :: Python :: 3 :: Only
Classifier: Topic :: Software Development :: Libraries
Requires-Python: >=3.8
License-File: LICENSE
Requires-Dist: PyYAML >=6.0.1
